README.rst
setup.py
xUnique.py
xUnique.egg-info/PKG-INFO
xUnique.egg-info/SOURCES.txt
xUnique.egg-info/dependency_links.txt
xUnique.egg-info/entry_points.txt
xUnique.egg-info/top_level.txt