Metadata-Version: 1.1
Name: xUnique
Version: 4.1.2
Summary: A converter of the Xcode project file to make merging it much easier in VCS
Home-page: https://github.com/truebit/xUnique
Author: Xiao Wang
Author-email: wangxiao8611@gmail.com
License: Apache License, Version 2.0
Keywords: Xcode project file,pbxproj,resolve merge conflict
Platform: UNKNOWN
Classifier: Development Status :: 5 - Production/Stable
Classifier: Intended Audience :: Developers
Classifier: License :: OSI Approved :: Apache Software License
Classifier: Topic :: Software Development :: Build Tools
Classifier: Topic :: Software Development :: Version Control
Classifier: Programming Language :: Objective C
Classifier: Programming Language :: Python :: 2
Classifier: Programming Language :: Python :: 2.7
